forwarder/__init__.py
forwarder/__main__.py
forwarder/_psockmixin.py
forwarder/api.py
forwarder/example-config.yaml
forwarder/hook.py
forwarder/psocket.py
forwarder/version.py
forwarder/worker.py
forwarder/cfg/__init__.py
forwarder/cfg/addr.py
forwarder/cfg/file.py
forwarder/cfg/host.py
forwarder/cfg/options.py
forwarder/cfg/port.py
forwarder/cfg/ports.py
forwarder/cfg/ssltls.py
forwarder/tcp/__init__.py
forwarder/tcp/listener.py
forwarder/tcp/transfer.py
forwarder/tcp/worker.py
forwarder/udp/__init__.py
forwarder/udp/listener.py
forwarder/udp/worker.py
forwarder-0.12.35.dist-info/METADATA
forwarder-0.12.35.dist-info/RECORD
forwarder-0.12.35.dist-info/WHEEL
forwarder-0.12.35.dist-info/entry_points.txt
forwarder-0.12.35.dist-info/top_level.txt
pyforwarder/__init__.py
pyforwarder/__main__.py
pyforwarder/api.py
pyforwarder/example-config.yaml
pyforwarder/psocket.py
pyforwarder/version.py
pyforwarder/worker.py
pyforwarder/cfg/__init__.py
pyforwarder/cfg/addr.py
pyforwarder/cfg/file.py
pyforwarder/cfg/host.py
pyforwarder/cfg/options.py
pyforwarder/cfg/port.py
pyforwarder/cfg/ports.py
pyforwarder/cfg/ssltls.py
pyforwarder/tcp/__init__.py
pyforwarder/tcp/listener.py
pyforwarder/tcp/transfer.py
pyforwarder/tcp/worker.py
pyforwarder/udp/__init__.py
pyforwarder/udp/listener.py
pyforwarder/udp/worker.py
