Metadata-Version: 2.1
Name: forwarder
Version: 0.12.35
Summary: forwarder a raw socket proxy with optional SSL/TLS termination and trace capability
Home-page: https://github.com/pe2mbs/pyforwarder
Author: Marc Bertens-Nguyen
Author-email: m.bertens@pe2mbs.nl
License: UNKNOWN
Project-URL: Bug Tracker, https://github.com/pe2mbs/pyforwarder/íssues
Project-URL: Documentation, https://github.com/pe2mbs/pyforwarder/wiki
Project-URL: Source Code, https://github.com/pe2mbs/pyforwarder
Keywords: forward proxy TCP UDP SSL/TLS
Platform: UNKNOWN
Classifier: Programming Language :: Python :: 3.6
Classifier: Programming Language :: Python :: 3.7
Classifier: Programming Language :: Python :: 3.8
Classifier: Programming Language :: Python :: 3.9
Classifier: Topic :: Communications
Classifier: Topic :: Education :: Testing
Classifier: Topic :: Internet
Classifier: Topic :: Internet :: Proxy Servers
Classifier: Topic :: Software Development
Classifier: Topic :: Utilities
Classifier: Natural Language :: English
Classifier: License :: OSI Approved :: GNU General Public License v2 (GPLv2)
Classifier: Operating System :: OS Independent
Requires-Python: >=3.6
Requires-Dist: pyyaml
